examples/monitor_async.py
tinytuya_async/__init__.py
tinytuya_async/scanner_async.py
tinytuya_async/core/DeviceAsync.py
tinytuya_async/core/__init__.py
tinytuya_async-0.0.3.dist-info/METADATA
tinytuya_async-0.0.3.dist-info/WHEEL
tinytuya_async-0.0.3.dist-info/top_level.txt
tinytuya_async-0.0.3.dist-info/RECORD
