Metadata-Version: 2.4
Name: tinytuya_async
Version: 0.0.3
Summary: TinyTuya Async
Project-URL: Homepage, https://github.com/3735943886/tinytuya_async
Requires-Python: >=3.8
Requires-Dist: asyncio
Requires-Dist: tinytuya
